resclu/__init__.py
resclu/resclu.py
resclu-0.1.1.dist-info/METADATA
resclu-0.1.1.dist-info/WHEEL
resclu-0.1.1.dist-info/entry_points.txt
resclu-0.1.1.dist-info/top_level.txt
resclu-0.1.1.dist-info/RECORD
