Metadata-Version: 2.1
Name: resclu
Version: 0.1.1
Summary: php is used to cluster data to train
Home-page: https://github.com/zondaxyz/resclu
Author: QIJUN GAO,BOYU CHEN and YIZHE XU
Author-email: 10210350465@stu.ecnu.edu.cn
License: MIT
Classifier: Development Status :: 3 - Alpha
Classifier: Intended Audience :: Developers
Classifier: License :: OSI Approved :: MIT License
Classifier: Programming Language :: Python
Classifier: Programming Language :: Python :: 3
Classifier: Programming Language :: Python :: 3.6
Classifier: Programming Language :: Python :: 3.7
Classifier: Programming Language :: Python :: 3.8
Classifier: Programming Language :: Python :: 3.9
Requires-Dist: numpy
Requires-Dist: pandas
Requires-Dist: scikit-learn
Requires-Dist: joblib
Requires-Dist: kneed
